tesseral_flask/__init__.py
tesseral_flask/context.py
tesseral_flask/credentials.py
tesseral_flask/errors.py
tesseral_flask/middleware.py
tesseral_flask/py.typed
tesseral_flask-0.0.7.dist-info/METADATA
tesseral_flask-0.0.7.dist-info/WHEEL
tesseral_flask-0.0.7.dist-info/RECORD
